CHANGES.rst
README.rst
setup.py
bobtemplates/__init__.py
bobtemplates.kotti.egg-info/PKG-INFO
bobtemplates.kotti.egg-info/SOURCES.txt
bobtemplates.kotti.egg-info/dependency_links.txt
bobtemplates.kotti.egg-info/namespace_packages.txt
bobtemplates.kotti.egg-info/not-zip-safe
bobtemplates.kotti.egg-info/requires.txt
bobtemplates.kotti.egg-info/top_level.txt
bobtemplates/kotti/__init__.py
bobtemplates/kotti/theme/.mrbob.ini
bobtemplates/kotti/theme/CHANGES.rst
bobtemplates/kotti/theme/README.rst.bob
bobtemplates/kotti/theme/development.ini.bob
bobtemplates/kotti/theme/setup.cfg.bob
bobtemplates/kotti/theme/setup.py.bob
bobtemplates/kotti/theme/+package.name+/__init__.py.bob
bobtemplates/kotti/theme/+package.name+/static/css/README
bobtemplates/kotti/theme/+package.name+/static/img/README
bobtemplates/kotti/theme/+package.name+/static/img/glyphicons-halflings-white.png
bobtemplates/kotti/theme/+package.name+/static/img/glyphicons-halflings.png
bobtemplates/kotti/theme/+package.name+/static/js/README